setup.py
ett_ds/__init__.py
ett_ds/cleanser.py
ett_ds/constants.py
ett_ds/helper.py
ett_ds/predictor.py
ett_ds/transformer.py
ett_ds.egg-info/PKG-INFO
ett_ds.egg-info/SOURCES.txt
ett_ds.egg-info/dependency_links.txt
ett_ds.egg-info/not-zip-safe
ett_ds.egg-info/top_level.txt