Metadata-Version: 1.0
Name: ett-ds
Version: 0.1
Summary: Emerging Technologies Team Data Science Package
Home-page: https://git.un.org/gsd/unite.un.org.ds.core
Author: United Nations ETT
Author-email: ett@un.org
License: MIT
Platform: UNKNOWN
